mlflow_pyfunc_server/__init__.py
mlflow_pyfunc_server/basehandler.py
mlflow_pyfunc_server/cli.py
mlflow_pyfunc_server/config.py
mlflow_pyfunc_server/server.py
mlflow_pyfunc_server/serverapp.py
mlflow_pyfunc_server-0.3.10.dist-info/LICENCE
mlflow_pyfunc_server-0.3.10.dist-info/METADATA
mlflow_pyfunc_server-0.3.10.dist-info/WHEEL
mlflow_pyfunc_server-0.3.10.dist-info/entry_points.txt
mlflow_pyfunc_server-0.3.10.dist-info/top_level.txt
mlflow_pyfunc_server-0.3.10.dist-info/RECORD
