Metadata-Version: 2.1
Name: mlflow-pyfunc-server
Version: 0.3.10
Summary: UNKNOWN
Home-page: https://github.com/VK/mlflow-pyfunc-server
License: MIT
Keywords: mlflow pyfunc
Platform: UNKNOWN
License-File: LICENCE
Requires-Dist: mlflow
Requires-Dist: uvicorn
Requires-Dist: fastapi
Requires-Dist: configargparse
Requires-Dist: apscheduler
